combinenet/__init__.py
combinenet/ase.py
combinenet/charge.py
combinenet/combine.py
combinenet/dataloader.py
combinenet/delta.py
combinenet/dispersion.py
combinenet/net.py
combinenet/sf.py
combinenet/utils.py
combinenet-1.0.0.dist-info/licenses/LICENSE
combinenet-1.0.0.dist-info/METADATA
combinenet-1.0.0.dist-info/WHEEL
combinenet-1.0.0.dist-info/top_level.txt
combinenet-1.0.0.dist-info/RECORD
