Metadata-Version: 2.4
Name: combinenet
Version: 1.0.0
Author-email: Nguyen Thien Phuc Tu <phuctu@cmail.carleton.ca>
License: MIT License
Keywords: machine learning,MLP,neural network potential,NNP
Requires-Python: >=3.9
License-File: LICENSE
Requires-Dist: numpy>=1.26.4
Requires-Dist: pandas>=2.2.2
Requires-Dist: torch>=2.4.0
Requires-Dist: h5py>=3.11.0
Requires-Dist: scikit-learn>=1.5.1
Requires-Dist: tqdm>=4.66.4
Requires-Dist: ase>=3.1
Dynamic: license-file
